unit_run/__init__.py
unit_run/cli.py
unit_run/components.py
unit_run/utils.py
unit_run-0.0.7.dist-info/LICENSE
unit_run-0.0.7.dist-info/METADATA
unit_run-0.0.7.dist-info/WHEEL
unit_run-0.0.7.dist-info/entry_points.txt
unit_run-0.0.7.dist-info/top_level.txt
unit_run-0.0.7.dist-info/RECORD
