Metadata-Version: 2.1
Name: unit-run
Version: 0.0.7
Summary: Easy to inspect, store and reperform unit running process.
Home-page: https://github.com/Lingfei-He/unit-run
Author: Lingfei He
Author-email: Lingfei He <lingfei@tju.edu.cn>
Project-URL: Homepage, https://github.com/Lingfei-He/unit-run
Project-URL: Bug Tracker, https://github.com/Lingfei-He/unit-run/issues
Classifier: Programming Language :: Python :: 3
Classifier: License :: OSI Approved :: MIT License
Classifier: Operating System :: OS Independent
Requires-Python: >=3.7
License-File: LICENSE
